das_atom_db/__init__.py
das_atom_db/adapters/__init__.py
das_atom_db/adapters/redis_mongo/__init__.py
das_atom_db/adapters/redis_mongo/db.py
das_atom_db/adapters/redis_mongo/schemas.py
das_atom_db/i_database.py
das_atom_db/utils/__init__.py
das_atom_db/utils/expression_hasher.py
das_atom_db-0.1.0.dist-info/METADATA
das_atom_db-0.1.0.dist-info/WHEEL
das_atom_db-0.1.0.dist-info/RECORD
